MANIFEST.in
README.md
requirements-dev.txt
requirements.txt
setup.cfg
setup.py
translater/__init__.py
translater/cli.py
translater/energydataframe.py
translater/energyseries.py
translater/idfclass.py
translater/reportdata.py
translater/schedule.py
translater/settings.py
translater/trnsys.py
translater/utils.py
translater.egg-info/PKG-INFO
translater.egg-info/SOURCES.txt
translater.egg-info/dependency_links.txt
translater.egg-info/entry_points.txt
translater.egg-info/requires.txt
translater.egg-info/top_level.txt
translater/ressources/NewFileTemplate.d18
translater/ressources/W74-lib.dat
translater/ressources/originBUISketchUp.idf