Metadata-Version: 2.1
Name: translater
Version: 1.0.4
Summary: Convert IDF file (EnergyPlus) to BUI file (TRNBuild)
Home-page: https://github.com/louisleroy5/translater
Author: Louis Leroy
Author-email: louis.leroy@polymtl.ca
License: -
Keywords: Building archetypes
Platform: UNKNOWN
Requires-Python: >=3.6
Provides-Extra: dev
